wand_cli-2.4.9.data/scripts/wand
wandbox/__init__.py
wandbox/__main__.py
wandbox/colorschemes/__init__.py
wandbox/colorschemes/dracula.py
wandbox/colorschemes/gruvbox.py
wandbox/colorschemes/nord.py
wandbox/commands/__init__.py
wandbox/commands/base.py
wandbox/commands/frombuffer.py
wandbox/commands/fromfile.py
wandbox/commands/frominput.py
wandbox/utilities/__init__.py
wandbox/utilities/compilers.py
wandbox/utilities/constants.py
wandbox/utilities/lang_extensions.py
wandbox/utilities/maketable.py
wandbox/utilities/utils.py
wand_cli-2.4.9.dist-info/LICENSE
wand_cli-2.4.9.dist-info/METADATA
wand_cli-2.4.9.dist-info/WHEEL
wand_cli-2.4.9.dist-info/top_level.txt
wand_cli-2.4.9.dist-info/RECORD
