Metadata-Version: 2.1
Name: wand-cli
Version: 2.4.9
Summary: A cli tool with an in-place terminal editor to compile over 27 languages instantly using the wandbox api.
Home-page: https://github.com/v1nam/wand-cli
Author: vinam
Author-email: vinamraj01@gmail.com
License: UNKNOWN
Keywords: wandbox cli compile run compiler
Platform: UNKNOWN
Classifier: Programming Language :: Python :: 3
Classifier: License :: OSI Approved :: MIT License
Requires-Python: >=3.8
Requires-Dist: requests (==2.25.1)
Requires-Dist: Pygments (==2.7.4)
Requires-Dist: prompt-toolkit (==3.0.11)
Requires-Dist: rich (==9.8.2)
Requires-Dist: argparse
